NOTICE
hive_metastore/constants.py
hive_metastore/__init__.py
hive_metastore/ttypes.py
hive_metastore/ThriftHiveMetastore.py
pyiceberg-0.8.1.dist-info/RECORD
pyiceberg-0.8.1.dist-info/LICENSE
pyiceberg-0.8.1.dist-info/WHEEL
pyiceberg-0.8.1.dist-info/entry_points.txt
pyiceberg-0.8.1.dist-info/NOTICE
pyiceberg-0.8.1.dist-info/METADATA
pyiceberg/transforms.py
pyiceberg/manifest.py
pyiceberg/partitioning.py
pyiceberg/conversions.py
pyiceberg/serializers.py
pyiceberg/__init__.py
pyiceberg/types.py
pyiceberg/typedef.py
pyiceberg/py.typed
pyiceberg/exceptions.py
pyiceberg/schema.py
pyiceberg/catalog/dynamodb.py
pyiceberg/catalog/rest.py
pyiceberg/catalog/__init__.py
pyiceberg/catalog/glue.py
pyiceberg/catalog/hive.py
pyiceberg/catalog/noop.py
pyiceberg/catalog/sql.py
pyiceberg/io/pyarrow.py
pyiceberg/io/__init__.py
pyiceberg/io/fsspec.py
pyiceberg/utils/lazydict.py
pyiceberg/utils/truncate.py
pyiceberg/utils/concurrent.py
pyiceberg/utils/config.py
pyiceberg/utils/parsing.py
pyiceberg/utils/properties.py
pyiceberg/utils/deprecated.py
pyiceberg/utils/schema_conversion.py
pyiceberg/utils/bin_packing.py
pyiceberg/utils/__init__.py
pyiceberg/utils/decimal.py
pyiceberg/utils/singleton.py
pyiceberg/utils/datetime.py
pyiceberg/cli/console.py
pyiceberg/cli/__init__.py
pyiceberg/cli/output.py
pyiceberg/avro/decoder.py
pyiceberg/avro/decoder_fast.pyi
pyiceberg/avro/decoder_fast.pypy39-pp73-darwin.so
pyiceberg/avro/decoder_basic.c
pyiceberg/avro/__init__.py
pyiceberg/avro/decoder_fast.cpython-312-darwin.so
pyiceberg/avro/encoder.py
pyiceberg/avro/reader.py
pyiceberg/avro/file.py
pyiceberg/avro/decoder_fast.pyx
pyiceberg/avro/decoder_fast.cpython-311-darwin.so
pyiceberg/avro/resolver.py
pyiceberg/avro/decoder_fast.cpython-39-darwin.so
pyiceberg/avro/writer.py
pyiceberg/avro/decoder_fast.cpython-310-darwin.so
pyiceberg/avro/codecs/zstandard_codec.py
pyiceberg/avro/codecs/bzip2.py
pyiceberg/avro/codecs/deflate.py
pyiceberg/avro/codecs/snappy_codec.py
pyiceberg/avro/codecs/__init__.py
pyiceberg/avro/codecs/codec.py
pyiceberg/table/snapshots.py
pyiceberg/table/metadata.py
pyiceberg/table/name_mapping.py
